setup.cfg
setup.py
ebookkit/__init__.py
ebookkit/ebookkit.py
ebookkit/util.py
ebookkit.egg-info/PKG-INFO
ebookkit.egg-info/SOURCES.txt
ebookkit.egg-info/dependency_links.txt
ebookkit.egg-info/top_level.txt